day_9_fsm/vending_machine_fsm/vending_fsm.v
module vending_fsm (input clk,rst,input[4:0]in,output dispence ,change);//product cost=20,input cost only= 5 or 10


parameter [2:0]  idle=0,five=1,ten=2,fifteen=3,twenty=4,twentyfive=5;

reg [2:0] state,n_s;

always @ (posedge clk)begin
	if(rst)
		state<=idle;
	else 
		state<=n_s;
end

//state transition
always @ (*) begin
	case (state)
		idle:begin
			if (in==5'd5)
				n_s=five;
			else if (in==5'd10)
				n_s=ten;
			else
				n_s=idle;
		end

		five:begin
                        if (in==5'd5)
                                n_s=ten;
                        else if (in==5'd10)
                                n_s=fifteen;
                        else
                                n_s=five;
                end

		ten:begin
                        if (in==5'd5)
                                n_s=fifteen;
                        else if (in==5'd10)
                                n_s=twenty;
                        else
                                n_s=ten;
                end


		fifteen:begin
                        if (in==5'd5)
                                n_s=twenty;
                        else if (in==5'd10)
                                n_s=twentyfive;
                        else
                                n_s=fifteen;
                end


		twenty:n_s=idle;

		twentyfive:n_s=idle;

	endcase
end

assign dispence=(state==twenty)||(state==twentyfive);
assign change=(state==twentyfive);

endmodule

day_9_fsm/vending_machine_fsm/vending_fsm_tb.v
module vending_tb ();

reg clk,rst;
reg [4:0]in;
wire dispence ,change;


vending_fsm dut (clk,rst,in,dispence,change);
initial begin
	clk=0;
	forever #5 clk=~clk;
end

initial begin
	$monitor ("time=%0t|clk=%b| rst=%b| in=%b | dispence=%b | change=%b |",$time,clk,rst,in,dispence,change);
	$dumpfile("vending.vcd");
	$dumpvars();


	rst=1;#10;
	rst=0;
	in=5'd5;#10;
	in=5'd5;#10;
	in=5'd10;#10;
	#10;
	in=5'd10;#10;
	in=5'd5;#10;
	in=5'd10;#10;
	
	

	#1 $finish;

end



endmodule

day_9_fsm/vending_machine_fsm/vending.vcd
$date
	Mon Nov 10 10:33:49 2025
$end
$version
	Icarus Verilog
$end
$timescale
	1s
$end
$scope module vending_tb $end
$var wire 1 ! dispence $end
$var wire 1 " change $end
$var reg 1 # clk $end
$var reg 5 $ in [4:0] $end
$var reg 1 % rst $end
$scope module dut $end
$var wire 1 # clk $end
$var wire 1 ! dispence $end
$var wire 5 & in [4:0] $end
$var wire 1 % rst $end
$var wire 1 " change $end
$var parameter 3 ' fifteen $end
$var parameter 3 ( five $end
$var parameter 3 ) idle $end
$var parameter 3 * ten $end
$var parameter 3 + twenty $end
$var parameter 3 , twentyfive $end
$var reg 3 - n_s [2:0] $end
$var reg 3 . state [2:0] $end
$upscope $end
$upscope $end
$enddefinitions $end
$comment Show the parameter values. $end
$dumpall
b101 ,
b100 +
b10 *
b0 )
b1 (
b11 '
$end
#0
$dumpvars
bx .
bx -
bx &
1%
bx $
0#
x"
x!
$end
#5
b0 -
0!
0"
b0 .
1#
#10
b1 -
0#
b101 $
b101 &
0%
#15
b10 -
b1 .
1#
#20
0#
#25
b11 -
b10 .
1#
#30
b100 -
0#
b1010 $
b1010 &
#35
b0 -
1!
b100 .
1#
#40
0#
#45
b10 -
0!
b0 .
1#
#50
0#
#55
b100 -
b10 .
1#
#60
b11 -
0#
b101 $
b101 &
#65
b100 -
b11 .
1#
#70
b101 -
0#
b1010 $
b1010 &
#75
b0 -
1!
1"
b101 .
1#
