day_9_fsm/moore_sequence_detector/moore_1011.v
module moore_1011 (input clk,rst,in,output out);

parameter [2:0] s0=0,s1=1,s2=2,s3=3,s4=4;   //s3 --->seq detected   in moore state output depend on present state if fsm in s3 means seg detected;

reg[2:0] state,n_s;


always @ (posedge clk)begin		//async rst;
	if (rst)
	       state<=s0;	//idle ;
        else
	       state<=n_s;
end

always @ (*) begin
	case (state)
		s0:n_s=in?s1:s0;	//idle
		s1:n_s=in?s1:s2;	//1 detected
		s2:n_s=in?s3:s0;	//10 detected
		s3:n_s=in?s4:s0;	//101 detected
		s4:n_s=in?s1:s0;	//1011 detected
	endcase
end
assign out=(state==s4);
endmodule

day_9_fsm/moore_sequence_detector/moore_1011_tb.v

module moore_tb ();

reg clk,rst,in;
wire out;

moore_1011 test (clk,rst,in,out);



initial begin
	clk=0;
	forever  #5 clk=~clk;
end



initial begin
	$monitor("time=%0t | clk=%b |rst=%b | in=%b | out=%b",$time,clk,rst,in,out);
	$dumpfile("moore_1011.vcd");
	$dumpvars;


	rst=1;in=1;#10;
	rst=0;
	in=1;#10;
	in=1;#10;
	in=0;#10;
	in=0;#10;
	in=1;#10;
	in=0;#10;
	in=1;#10;
	in=1;#10;
	in=1;#10;

	#1 $finish;



end
endmodule

day_9_fsm/moore_sequence_detector/moore_1011.vcd
$date
	Sat Nov  8 06:40:22 2025
$end
$version
	Icarus Verilog
$end
$timescale
	1s
$end
$scope module moore_tb $end
$var wire 1 ! out $end
$var reg 1 " clk $end
$var reg 1 # in $end
$var reg 1 $ rst $end
$scope module test $end
$var wire 1 " clk $end
$var wire 1 # in $end
$var wire 1 $ rst $end
$var wire 1 ! out $end
$var parameter 3 % s0 $end
$var parameter 3 & s1 $end
$var parameter 3 ' s2 $end
$var parameter 3 ( s3 $end
$var parameter 3 ) s4 $end
$var reg 3 * n_s [2:0] $end
$var reg 3 + state [2:0] $end
$upscope $end
$upscope $end
$enddefinitions $end
$comment Show the parameter values. $end
$dumpall
b100 )
b11 (
b10 '
b1 &
b0 %
$end
#0
$dumpvars
bx +
bx *
1$
1#
0"
x!
$end
#5
b1 *
0!
b0 +
1"
#10
0"
0$
#15
b1 +
1"
#20
0"
#25
1"
#30
b10 *
0"
0#
#35
b0 *
b10 +
1"
#40
0"
#45
b0 +
1"
#50
b1 *
0"
1#
#55
b1 +
1"
#60
b10 *
0"
0#
#65
b0 *
b10 +
1"
#70
b11 *
0"
1#
#75
b100 *
b11 +
1"
#80
0"
#85
b1 *
1!
b100 +
1"
#90
0"
#95
0!
b1 +
1"
