day_9_fsm/moore_sequence_detector/moore_1011.v
module moore_1011 (input clk,rst,in,output out);

parameter [2:0] s0=0,s1=1,s2=2,s3=3,s4=4;   //s3 --->seq detected   in moore state output depend on present state if fsm in s3 means seg detected;

reg[2:0] state,n_s;


always @ (posedge clk)begin		//async rst;
	if (rst)
	       state<=s0;	//idle ;
        else
	       state<=n_s;
end

always @ (*) begin
	case (state)
		s0:n_s=in?s1:s0;	//idle
		s1:n_s=in?s1:s2;	//1 detected
		s2:n_s=in?s3:s0;	//10 detected
		s3:n_s=in?s4:s0;	//101 detected
		s4:n_s=in?s1:s0;	//1011 detected
	endcase
end
assign out=(state==s4);
endmodule

day_9_fsm/moore_sequence_detector/moore_1011_tb.v

module moore_tb ();

reg clk,rst,in;
wire out;

moore_1011 test (clk,rst,in,out);



reg [3:0] in_store;
reg out_exp;


always @ (posedge clk)begin
	if (rst)
		in_store<=4'b0;
	else
		in_store<={in_store[2:0],in};
end

always @ (*)begin
       if(in_store==4'b1011)
	       out_exp<=1;
       else
	       out_exp<=0;
end


always @ (posedge clk) begin
	if (out!=out_exp)begin
		//$display ("Mismatch Occured");
		$display ("$time=%0t | out=%b | exp=%b | input_sequence=%b|fail",$time,out,out_exp,in_store);
	
		$finish;

	end
	else if (out==1'b1)
		$display ("$time=%0t | out=%b | exp=%b | input_sequence=%b|pass",$time,out,out_exp,in_store);
	
end



initial begin
	clk=0;
	forever  #5 clk=~clk;
end



initial begin
	//$monitor("time=%0t | clk=%b |rst=%b | in=%b | out=%b",$time,clk,rst,in,out);
	
	$dumpfile("moore_1011.vcd");
	$dumpvars;


	rst=1;in=1;#10;
	rst=0;
	in=1;#10;
	in=1;#10;
	in=0;#10;
	in=0;#10;
	in=1;#10;
	in=0;#10;
	in=1;#10;
	in=1;#10;
	in=1;#10;
	in=0;#10;
	in=1;#10;
	in=1;#10;
	in=0;#10;
	in=1;#10;
	in=1;#10;
	repeat (50)begin
		@(posedge clk)in=$random%2;
		
	end





	#2 $finish;



end
endmodule

day_9_fsm/moore_sequence_detector/moore_1011.vcd
$date
	Mon Nov 10 10:21:44 2025
$end
$version
	Icarus Verilog
$end
$timescale
	1s
$end
$scope module moore_tb $end
$var wire 1 ! out $end
$var reg 1 " clk $end
$var reg 1 # in $end
$var reg 4 $ in_store [3:0] $end
$var reg 1 % out_exp $end
$var reg 1 & rst $end
$scope module test $end
$var wire 1 " clk $end
$var wire 1 # in $end
$var wire 1 & rst $end
$var wire 1 ! out $end
$var parameter 3 ' s0 $end
$var parameter 3 ( s1 $end
$var parameter 3 ) s2 $end
$var parameter 3 * s3 $end
$var parameter 3 + s4 $end
$var reg 3 , n_s [2:0] $end
$var reg 3 - state [2:0] $end
$upscope $end
$upscope $end
$enddefinitions $end
$comment Show the parameter values. $end
$dumpall
b100 +
b11 *
b10 )
b1 (
b0 '
$end
#0
$dumpvars
bx -
bx ,
1&
x%
bx $
1#
0"
x!
$end
#5
0%
b1 ,
0!
b0 -
b0 $
1"
#10
0"
0&
#15
b1 $
b1 -
1"
#20
0"
#25
b11 $
1"
#30
b10 ,
0"
0#
#35
b0 ,
b110 $
b10 -
1"
#40
0"
#45
b0 -
b1100 $
1"
#50
b1 ,
0"
1#
#55
b1001 $
b1 -
1"
#60
b10 ,
0"
0#
#65
b0 ,
b10 -
b10 $
1"
#70
b11 ,
0"
1#
#75
b100 ,
b101 $
b11 -
1"
#80
0"
#85
1%
b1 ,
1!
b100 -
b1011 $
1"
#90
0"
#95
0%
b111 $
0!
b1 -
1"
#100
b10 ,
0"
0#
#105
b0 ,
b10 -
b1110 $
1"
#110
b11 ,
0"
1#
#115
b100 ,
b1101 $
b11 -
1"
#120
0"
#125
1%
b1 ,
1!
b100 -
b1011 $
1"
#130
b0 ,
0"
0#
#135
0%
b110 $
0!
b0 -
1"
#140
b1 ,
0"
1#
#145
b1 -
b1101 $
1"
#150
0"
#155
1%
b1011 $
1"
#160
0"
#165
0%
b110 $
b10 ,
0#
1"
