day_8_register/parallel_in_4bit/parallel_in.v
module d_ff(input d,clk, rst,output reg q);

always @ (posedge clk or posedge rst)//asynchronous reset
   begin
	if(rst)
		q=0;//if rst=1 then q=0 is executed
	else
	       	q=d;
   end

endmodule



/*module parallel_in (input clk,rst,input [3:0] a,output  [3:0]q);

genvar i;
generate
	for (i=0;i<4;i=i+1)begin:bit_reg
		d_ff inst (a[i],clk,rst,q[i]);
	end
endgenerate

endmodule*/	


module parallel_in #(parameter n=4 ) (input clk,rst,input [n-1:0] a,output  [n-1:0]q);

genvar i;
generate
        for (i=0;i<n;i=i+1)begin:bit_reg
                d_ff inst (a[i],clk,rst,q[i]);
        end
endgenerate

endmodule

day_8_register/pipo/parallel_in_tb.v
module parallel_in_tb ();
parameter n=3;
reg clk,rst;
reg [n-1:0]a;
wire [n-1:0]q;


parallel_in #(.n(n)) inst1 (clk,rst,a,q);


initial begin
	clk=0;
	forever #5 clk=~clk;
end


initial begin
		$monitor("Time = %0t | clk = %b | rst = %b | a = %b | q = %b ",$time, clk, rst, a, q);
		$dumpfile("parallel_in.vcd");
		$dumpvars();


		rst=1;a=$random;#10;
		rst=0;
		a=$random;#10;
		repeat (15)begin
			a=$random;#10;
		end	

		#6 $finish;
	end

	endmodule

day_8_register/parallel_in_4bit/parallel_in.vcd
$date
	Mon Oct 27 16:36:36 2025
$end
$version
	Icarus Verilog
$end
$timescale
	1s
$end
$scope module parallel_in_tb $end
$var wire 3 ! q [2:0] $end
$var parameter 32 " n $end
$var reg 3 # a [2:0] $end
$var reg 1 $ clk $end
$var reg 1 % rst $end
$scope module inst1 $end
$var wire 3 & a [2:0] $end
$var wire 1 $ clk $end
$var wire 1 % rst $end
$var wire 3 ' q [2:0] $end
$var parameter 32 ( n $end
$scope begin bit_reg[0] $end
$var parameter 2 ) i $end
$scope module inst $end
$var wire 1 $ clk $end
$var wire 1 * d $end
$var wire 1 % rst $end
$var reg 1 + q $end
$upscope $end
$upscope $end
$scope begin bit_reg[1] $end
$var parameter 2 , i $end
$scope module inst $end
$var wire 1 $ clk $end
$var wire 1 - d $end
$var wire 1 % rst $end
$var reg 1 . q $end
$upscope $end
$upscope $end
$scope begin bit_reg[2] $end
$var parameter 3 / i $end
$scope module inst $end
$var wire 1 $ clk $end
$var wire 1 0 d $end
$var wire 1 % rst $end
$var reg 1 1 q $end
$upscope $end
$upscope $end
$upscope $end
$upscope $end
$enddefinitions $end
$comment Show the parameter values. $end
$dumpall
b10 /
b1 ,
b0 )
b11 (
b11 "
$end
#0
$dumpvars
01
10
0.
0-
0+
0*
b0 '
b100 &
1%
0$
b100 #
b0 !
$end
#5
1$
#10
1*
00
0$
b1 #
b1 &
0%
#15
b1 !
b1 '
1+
1$
#20
0$
#25
1$
#30
1-
0$
b11 #
b11 &
#35
b11 !
b11 '
1.
1$
#40
0-
10
0$
b101 #
b101 &
#45
11
b101 !
b101 '
0.
1$
#50
0$
#55
1$
#60
0$
#65
1$
#70
0*
1-
00
0$
b10 #
b10 &
#75
0+
1.
b10 !
b10 '
01
1$
#80
1*
0-
0$
b1 #
b1 &
#85
0.
b1 !
b1 '
1+
1$
#90
10
0$
b101 #
b101 &
#95
b101 !
b101 '
11
1$
#100
0*
1-
0$
b110 #
b110 &
#105
1.
b110 !
b110 '
0+
1$
#110
1*
0-
0$
b101 #
b101 &
#115
1+
b101 !
b101 '
0.
1$
#120
0$
#125
1$
#130
0*
0$
b100 #
b100 &
#135
b100 !
b100 '
0+
1$
#140
1*
00
0$
b1 #
b1 &
#145
01
b1 !
b1 '
1+
1$
#150
0*
1-
10
0$
b110 #
b110 &
#155
0+
1.
b110 !
b110 '
11
1$
#160
1*
0-
0$
b101 #
b101 &
#165
0.
b101 !
b101 '
1+
1$
