day_2_comb/full_adder/full_adder.v
module full_adder(input a,b,cin, output sum,carry);
assign sum=(a^b^cin);
assign carry=(a & b) | (b & cin) | (a & cin);
endmodule

day_2_comb/full_adder/full_adder_tb.v
module full_adder_tb();
reg a,b,cin;
wire sum,carry;


full_adder inst(a,b,cin,sum,carry);


initial begin
$monitor("%0t|a-%b|b=%b|cin=%b|sum=%b|carry=%b",$time,a,b,cin,sum,carry);
$dumpfile("wave.vcd");
$dumpvars;
a=0;b=0;cin=0;#5;
a=0;b=0;cin=1;#5;
a=0;b=1;cin=0;#5;
a=0;b=1;cin=1;#5;
a=1;b=0;cin=0;#5;
a=1;b=0;cin=1;#5;
a=1;b=1;cin=0;#5;
a=1;b=1;cin=1;#5;
$finish;
end 
endmodule

day_2_comb/full_adder/wave.vcd
$date
	Fri Oct 10 18:39:05 2025
$end
$version
	Icarus Verilog
$end
$timescale
	1s
$end
$scope module full_adder_tb $end
$var wire 1 ! sum $end
$var wire 1 " carry $end
$var reg 1 # a $end
$var reg 1 $ b $end
$var reg 1 % cin $end
$scope module inst $end
$var wire 1 # a $end
$var wire 1 $ b $end
$var wire 1 " carry $end
$var wire 1 % cin $end
$var wire 1 ! sum $end
$upscope $end
$upscope $end
$enddefinitions $end
$comment Show the parameter values. $end
$dumpall
$end
#0
$dumpvars
0%
0$
0#
0"
0!
$end
#5
1!
1%
#10
0%
1$
#15
1"
0!
1%
#20
0"
1!
0%
0$
1#
#25
1"
0!
1%
#30
0%
1$
#35
1!
1%
