day5_latch/jk_latch/jk_latch.v
module jk_latch (input clk,rst,j,k,output reg q);

always @ (*)
begin
	if (rst)
		q<=0;
	else begin
		if (clk)  begin

			case({j,k})
			2'b00:q<=q;     //no change
			2'b01:q<=1'b0;  //resert condition
			2'b10:q<=1'b1;  //set condition
			2'b11:q<=~q;    //toggle
			endcase
		end
		
		else
			q<=q;


	end
end 
endmodule

day_5_latch/jk_latch/jk_latch_tb.v
module jk_latch_tb();


reg clk,rst,j,k;
wire q;


jk_latch test (clk,rst,j,k,q);


initial begin
	clk=0;
	forever #5 clk=~clk;

end

initial begin

	$monitor("time=%0t| clk=%b| rst=%b| j=%b| k=%b| q=%b",$time,clk,rst,j,k,q);
	$dumpfile("jk_latch.vcd");
	$dumpvars;


	rst=1;j=1;k=0;
	#3 rst=0;

	repeat (15) begin
		#2 {j,k}=$random%4;

	end
	

	#2 $finish;

end

endmodule

day_5_latch/jk_latch/jk_latch.vcd
$date
	Fri Oct 24 04:39:55 2025
$end
$version
	Icarus Verilog
$end
$timescale
	1s
$end
$scope module jk_latch_tb $end
$var wire 1 ! q $end
$var reg 1 " clk $end
$var reg 1 # j $end
$var reg 1 $ k $end
$var reg 1 % rst $end
$scope module test $end
$var wire 1 " clk $end
$var wire 1 # j $end
$var wire 1 $ k $end
$var wire 1 % rst $end
$var reg 1 ! q $end
$upscope $end
$upscope $end
$enddefinitions $end
$comment Show the parameter values. $end
$dumpall
$end
#0
$dumpvars
1%
0$
1#
0"
0!
$end
#3
0%
#5
0#
1"
#7
1$
#10
0"
#11
1#
#13
0#
#15
1"
#19
1!
1#
0$
#20
0"
#21
0#
1$
#25
1#
0$
1"
#27
0!
0#
1$
#30
0"
#31
0$
#33
1$
