day_9_fsm/traffic_light_controller/traffic_light_contrl.v
module traffic_light_controller(input clk,rst,output g_light,o_light,r_light);


parameter [1:0]  green =0,orange=1,red=2;

parameter g_time=10'd20,
o_time=10'd5,
r_time=10'd10;


reg[1:0] state,n_s;

reg [10:0] counter ;
wire zero_flag;



always @ (posedge clk)begin
	if (rst) begin
		state<=green;
		counter<=g_time;
	end
	else begin
		state<=n_s;
	 	if (counter!=0)
			counter<=counter-1;

		else begin
			case(state)
				green:counter=o_time;
				orange:counter=r_time;
				red:counter=g_time;

			endcase
		end
	end

			

end


always @ (*) begin

	n_s=state;
	case(state)

		green:begin
			if(counter==0)
				n_s=orange;
		end


		orange:begin
                        if (counter==0)
				n_s=red;
			else
				n_s=orange;
		end

		red:begin
                        if (counter==0)
				n_s=green;
			else
				n_s=red;
		end

	endcase

end


assign g_light =(state== green);
assign o_light =(state==orange);
assign r_light =(state==red);


endmodule

day_9_fsm/moore_sequence_detector/traffic_light_controller/traffic_contrl_tb.v
`timescale 1ns/1ps
module traffic_contrl_tb ();
reg clk,rst;
wire green_light ,orange_light,red_light;

traffic_light_controller #(.g_time(30),.o_time(5),.r_time(10)) dut (clk,rst,green_light ,orange_light,red_light);

initial begin
	clk=0;
	forever #5 clk=~clk;
end

initial begin
	$monitor ("time=%0t | clk=%b |rst=%b|green_light =%b|orange_light=%b|red_light=%b|",$time,clk,rst,green_light,orange_light,red_light);
	$dumpfile("traffic_contrl.vcd");
	$dumpvars();

	rst=1;#10;
	rst=0;#5;


	#501 $finish;
end

endmodule

day_9_fsm/moore_sequence_detector/traffic_light_controller/traffic_contrl.vcd
$date
	Mon Nov 10 02:47:34 2025
$end
$version
	Icarus Verilog
$end
$timescale
	1ps
$end
$scope module traffic_contrl_tb $end
$var wire 1 ! red_light $end
$var wire 1 " orange_light $end
$var wire 1 # green_light $end
$var reg 1 $ clk $end
$var reg 1 % rst $end
$scope module dut $end
$var wire 1 $ clk $end
$var wire 1 % rst $end
$var wire 1 ! r_light $end
$var wire 1 " o_light $end
$var wire 1 # g_light $end
$var parameter 32 & g_time $end
$var parameter 2 ' green $end
$var parameter 32 ( o_time $end
$var parameter 2 ) orange $end
$var parameter 32 * r_time $end
$var parameter 2 + red $end
$var reg 11 , counter [10:0] $end
$var reg 2 - n_s [1:0] $end
$var reg 2 . state [1:0] $end
$upscope $end
$upscope $end
$enddefinitions $end
$comment Show the parameter values. $end
$dumpall
b10 +
b1010 *
b1 )
b101 (
b0 '
b11110 &
$end
#0
$dumpvars
bx .
bx -
bx ,
1%
0$
x#
x"
x!
$end
#5000
b0 -
b11110 ,
1#
0"
0!
b0 .
1$
#10000
0$
0%
#15000
b11101 ,
1$
#20000
0$
#25000
b11100 ,
1$
#30000
0$
#35000
b11011 ,
1$
#40000
0$
#45000
b11010 ,
1$
#50000
0$
#55000
b11001 ,
1$
#60000
0$
#65000
b11000 ,
1$
#70000
0$
#75000
b10111 ,
1$
#80000
0$
#85000
b10110 ,
1$
#90000
0$
#95000
b10101 ,
1$
#100000
0$
#105000
b10100 ,
1$
#110000
0$
#115000
b10011 ,
1$
#120000
0$
#125000
b10010 ,
1$
#130000
0$
#135000
b10001 ,
1$
#140000
0$
#145000
b10000 ,
1$
#150000
0$
#155000
b1111 ,
1$
#160000
0$
#165000
b1110 ,
1$
#170000
0$
#175000
b1101 ,
1$
#180000
0$
#185000
b1100 ,
1$
#190000
0$
#195000
b1011 ,
1$
#200000
0$
#205000
b1010 ,
1$
#210000
0$
#215000
b1001 ,
1$
#220000
0$
#225000
b1000 ,
1$
#230000
0$
#235000
b111 ,
1$
#240000
0$
#245000
b110 ,
1$
#250000
0$
#255000
b101 ,
1$
#260000
0$
#265000
b100 ,
1$
#270000
0$
#275000
b11 ,
1$
#280000
0$
#285000
b10 ,
1$
#290000
0$
#295000
b1 ,
1$
#300000
0$
#305000
b1 -
b0 ,
1$
#310000
0$
#315000
0#
1"
b1 .
b1 -
b101 ,
1$
#320000
0$
#325000
b100 ,
1$
#330000
0$
#335000
b11 ,
1$
#340000
0$
#345000
b10 ,
1$
#350000
0$
#355000
b1 ,
1$
#360000
0$
#365000
b10 -
b0 ,
1$
#370000
0$
#375000
0"
1!
b10 .
b10 -
b1010 ,
1$
#380000
0$
#385000
b1001 ,
1$
#390000
0$
#395000
b1000 ,
1$
#400000
0$
#405000
b111 ,
1$
#410000
0$
#415000
b110 ,
1$
#420000
0$
#425000
b101 ,
1$
#430000
0$
#435000
b100 ,
1$
#440000
0$
#445000
b11 ,
1$
#450000
0$
#455000
b10 ,
1$
#460000
0$
#465000
b1 ,
1$
#470000
0$
#475000
b0 -
b0 ,
1$
#480000
0$
#485000
1#
0!
b0 .
b0 -
b11110 ,
1$
#490000
0$
#495000
b11101 ,
1$
#500000
0$
#505000
b11100 ,
1$
#510000
0$
#515000
b11011 ,
1$
