day_8_register/universal_shiftregister/universal.v
module universal 
(input clk,rst,r_serialin,l_serialin,
input [1:0]sel, 
input [3:0]parallel_in,
output reg [3:0]q,output reg out);


always @ (posedge clk or posedge rst)
begin
	if (rst)begin
		q<=0;
		out<=0;
	end
	else begin
		case(sel)
			2'b00:q<=q;			//00 -->no change
			2'b01:begin			//01 -->right shift	
				out<=q[0];
				q<={r_serialin,q[3:1]};
			end
			2'b10:begin			//10 -->lest shift
				out<=q[3];
				q={q[2:0],l_serialin};
			end
			2'b11:begin
				
				q<=parallel_in;#1;		//11 -->parallel load/in;
				out=q[0];
			end	
		endcase
end		

end				
endmodule

day_8_register/universal_shiftregister/universal_tb.v
module bidirectional_tb ();
reg clk,rst,r_serialin,l_serialin;
reg [1:0]sel;
reg [3:0]parallel_in;
wire [3:0]q;
wire out;


universal inst (clk,rst,r_serialin,l_serialin,sel,parallel_in,q,out);

initial begin
	clk=0;
end

always #5 clk=~clk;

//stimulus generation
initial begin
	$monitor("time=%0t |clk=%b |rst=%b| sel=%b | r_serialin=%b | l_serialin=%b | parallel_in=%b |q=%b| out=%b ",$time,clk,rst,sel,r_serialin,l_serialin,parallel_in,q,out);
	$dumpfile("universal.vcd");
	$dumpvars;

	rst=1;sel=10;#10;
	rst=0;
	repeat (6)begin
		r_serialin=$random;
		l_serialin=$random;
		#10;
	end
	sel=11;
	repeat (6)begin
		parallel_in=$random;
		#10;
	end	


	#2 $finish;
end

endmodule

day_8_register/universal_shiftregister/universal.vcd
$date
	Tue Oct 28 13:07:07 2025
$end
$version
	Icarus Verilog
$end
$timescale
	1s
$end
$scope module bidirectional_tb $end
$var wire 4 ! q [3:0] $end
$var wire 1 " out $end
$var reg 1 # clk $end
$var reg 1 $ l_serialin $end
$var reg 4 % parallel_in [3:0] $end
$var reg 1 & r_serialin $end
$var reg 1 ' rst $end
$var reg 2 ( sel [1:0] $end
$scope module inst $end
$var wire 1 # clk $end
$var wire 1 $ l_serialin $end
$var wire 4 ) parallel_in [3:0] $end
$var wire 1 & r_serialin $end
$var wire 1 ' rst $end
$var wire 2 * sel [1:0] $end
$var reg 1 " out $end
$var reg 4 + q [3:0] $end
$upscope $end
$upscope $end
$enddefinitions $end
$comment Show the parameter values. $end
$dumpall
$end
#0
$dumpvars
b0 +
b10 *
bx )
b10 (
1'
x&
bx %
x$
0#
0"
b0 !
$end
#5
1#
#10
0#
1$
0&
0'
#15
b1 !
b1 +
1#
#20
0#
1&
#25
b11 !
b11 +
1#
#30
0#
#35
b111 !
b111 +
1#
#40
0#
0$
#45
b1110 !
b1110 +
1#
#50
0#
1$
#55
1"
b1101 !
b1101 +
1#
#60
0#
0&
#65
b1011 !
b1011 +
1#
#70
0#
b1101 %
b1101 )
b11 (
b11 *
#75
b1101 !
b1101 +
1#
#80
0#
b1100 %
b1100 )
#85
b1100 !
b1100 +
1#
#86
0"
#90
0#
b1001 %
b1001 )
#95
b1001 !
b1001 +
1#
#96
1"
#100
0#
b110 %
b110 )
#105
b110 !
b110 +
1#
#106
0"
#110
0#
b101 %
b101 )
#115
b101 !
b101 +
1#
#116
1"
#120
0#
b1010 %
b1010 )
#125
b1010 !
b1010 +
1#
#126
0"
